pinterest_crawler/__init__.py
pinterest_crawler/config.py
pinterest_crawler/loop.py
pinterest_crawler/main.py
pinterest_crawler/pinterest_crawler.py
pinterest_crawler/scraper.py
pinterest_crawler-0.2.0.dist-info/LICENSE.md
pinterest_crawler-0.2.0.dist-info/METADATA
pinterest_crawler-0.2.0.dist-info/WHEEL
pinterest_crawler-0.2.0.dist-info/entry_points.txt
pinterest_crawler-0.2.0.dist-info/top_level.txt
pinterest_crawler-0.2.0.dist-info/RECORD
