Metadata-Version: 2.1
Name: pinterest-crawler
Version: 0.2.0
Summary: Pinterest Crawler: Download as many images as you want about the searched words
Home-page: https://github.com/SajjadAemmi/Pinterest-Crawler
Author: Sajjad Aemmi
Author-email: sajjadaemmi@gmail.com
License-File: LICENSE.md
Requires-Dist: requests
